setup.py
msgpack_rpc_python.egg-info/PKG-INFO
msgpack_rpc_python.egg-info/SOURCES.txt
msgpack_rpc_python.egg-info/dependency_links.txt
msgpack_rpc_python.egg-info/requires.txt
msgpack_rpc_python.egg-info/top_level.txt
msgpackrpc/__init__.py
msgpackrpc/_version.py
msgpackrpc/address.py
msgpackrpc/client.py
msgpackrpc/compat.py
msgpackrpc/error.py
msgpackrpc/future.py
msgpackrpc/loop.py
msgpackrpc/message.py
msgpackrpc/server.py
msgpackrpc/session.py
msgpackrpc/transport/__init__.py
msgpackrpc/transport/tcp.py
test/test_msgpackrpc.py