Metadata-Version: 1.0
Name: msgpack-rpc-python
Version: 0.3.0
Summary: MessagePack RPC
Home-page: https://github.com/msgpack/msgpack-rpc-python
Author: Masahiro Nakagawa
Author-email: repeatedly@gmail.com
License: Apache Software License
Platform: UNKNOWN
Classifier: Programming Language :: Python :: 2
Classifier: Programming Language :: Python :: 3
Classifier: License :: OSI Approved :: Apache Software License
